webloc2html.py
webloc2html-0.0.5.dist-info/METADATA
webloc2html-0.0.5.dist-info/WHEEL
webloc2html-0.0.5.dist-info/entry_points.txt
webloc2html-0.0.5.dist-info/RECORD
