Metadata-Version: 2.1
Name: webloc2html
Version: 0.0.5
Summary: Converts .webloc to .html
Project-URL: Homepage, https://github.com/blemli/webloc2html
Project-URL: Issues, https://github.com/blemli/webloc2html/issues
Author-email: Problemli GmbH <info@problem.li>
Classifier: License :: OSI Approved :: MIT License
Classifier: Operating System :: OS Independent
Classifier: Programming Language :: Python :: 3
Requires-Python: >=3.8
Requires-Dist: click>=8.1.7
Requires-Dist: requests>=2.31.0
